fakerlocationer/__init__.py
fakerlocationer/fakerlocationer.py
fakerlocationer-1.0.dist-info/METADATA
fakerlocationer-1.0.dist-info/WHEEL
fakerlocationer-1.0.dist-info/top_level.txt
fakerlocationer-1.0.dist-info/RECORD
