Metadata-Version: 2.1
Name: fakerlocationer
Version: 1.0
Summary: A simple class that can be used to fake Selenium Browser Geolocation
Home-page: https://github.com/kenevil1/fakerlocationer
Author: kenevil1
Author-email: no@email.com
License: UNKNOWN
Platform: UNKNOWN
Classifier: Programming Language :: Python :: 3
Classifier: License :: OSI Approved :: MIT License
Classifier: Operating System :: OS Independent
